studentresume/__init__.py
studentresume/fonts/ARIAL.TTF
studentresume/fonts/ARIALBD.TTF
studentresume/fonts/Calibri Bold.TTF
studentresume/fonts/Calibri Regular.ttf
studentresume/fonts/Cambria.ttf
studentresume/fonts/Futura Bold font.ttf
studentresume/fonts/GARMNDB.ttf
studentresume/fonts/Garamond Regular.ttf
studentresume/fonts/Helvetica-Bold.ttf
studentresume/fonts/Helvetica.ttf
studentresume/fonts/Inconsolata-Bold-Nerd.ttf
studentresume/fonts/Inconsolata-Bold.ttf
studentresume/fonts/Inconsolata-Regular-Nerd.ttf
studentresume/fonts/Inconsolata-Regular.ttf
studentresume/fonts/ROCK.TTF
studentresume/fonts/cambriab.ttf
studentresume/fonts/futur.ttf
studentresume/fonts/rockb.ttf
studentresume/fonts/times new roman bold.ttf
studentresume/fonts/times new roman.ttf
studentresume/fonts/verdana-bold.ttf
studentresume/fonts/verdana.ttf
studentresume/json_validator.py
studentresume/requiredFields.json
studentresume/resume.py
studentresume/run.py
studentresume/sample.resume.json
studentresume/schema.json
studentresume/testonepage.resume.json
studentresume/theme-schema.json
studentresume/themes/default.json
studentresume/themes/default2.json
studentresume/themes/default3.json
studentresume-0.8.3.dist-info/entry_points.txt
studentresume-0.8.3.dist-info/LICENSE
studentresume-0.8.3.dist-info/WHEEL
studentresume-0.8.3.dist-info/METADATA
studentresume-0.8.3.dist-info/RECORD
