Metadata-Version: 2.1
Name: studentresume
Version: 0.8.3
Summary: Student Resume Generator Python Package
Home-page: https://studentresume.org
License: MIT
Author: Diana Le
Author-email: dble@ualberta.ca
Requires-Python: >=3.8,<4.0
Classifier: License :: OSI Approved :: MIT License
Classifier: Programming Language :: Python :: 3
Classifier: Programming Language :: Python :: 3.8
Classifier: Programming Language :: Python :: 3.9
Classifier: Programming Language :: Python :: 3.10
Classifier: Programming Language :: Python :: 3.11
Requires-Dist: jsonschema (>=4.17.3,<5.0.0)
Requires-Dist: reportlab (>=3.6.12,<4.0.0)
Requires-Dist: rich (>=12.6.0,<13.0.0)
Requires-Dist: typer (>=0.7.0,<0.8.0)
Project-URL: Repository, https://github.com/open-uofa/studentresume
